gamelan_sequencer/__init__.py
gamelan_sequencer/__main__.py
gamelan_sequencer/gamelan.py
gamelan_sequencer/gamelan_score.py
gamelan_sequencer/section.py
gamelan_sequencer/tempo.py
gamelan_sequencer/wave_manager.py
gamelan_sequencer/samples/javanese_gamelan.json
gamelan_sequencer-1.2.0.dist-info/LICENSE
gamelan_sequencer-1.2.0.dist-info/METADATA
gamelan_sequencer-1.2.0.dist-info/WHEEL
gamelan_sequencer-1.2.0.dist-info/entry_points.txt
gamelan_sequencer-1.2.0.dist-info/top_level.txt
gamelan_sequencer-1.2.0.dist-info/RECORD
