Metadata-Version: 2.1
Name: gamelan-sequencer
Version: 1.2.0
Summary: Python Sequencer for Gamelan Music
Home-page: https://github.com/regosen/gamelan_sequencer
Author: Rego Sen
Author-email: regosen@gmail.com
License: MIT
Keywords: music songwriting indonesia javanese balinese kepatihan gamelan
Platform: UNKNOWN
Classifier: Development Status :: 4 - Beta
Classifier: Environment :: Console
Classifier: Intended Audience :: End Users/Desktop
Classifier: License :: OSI Approved :: MIT License
Classifier: Operating System :: OS Independent
Classifier: Programming Language :: Python
Classifier: Programming Language :: Python :: 2
Classifier: Programming Language :: Python :: 3
Classifier: Topic :: Multimedia :: Sound/Audio
Classifier: Topic :: Multimedia :: Sound/Audio :: Editors
License-File: LICENSE
Requires-Dist: scipy
